ingestion/README.rst
ingestion/__init__.py
ingestion/ingestion_apis/__init__.py
ingestion/ingestion_apis/asset_creation_api.py
ingestion/ingestion_apis/asset_db_api.py
ingestion/ingestion_apis/config.py
ingestion/ingestion_apis/container_api.py
ingestion/ingestion_apis/encryption_api.py
ingestion/ingestion_apis/gridfs_api.py
ingestion/ingestion_apis/policy_api.py
ingestion/ingestion_apis/policy_exception_apis.py
ingestion/ingestion_mongo_apis/__init__.py
ingestion/ingestion_mongo_apis/mongo_asset.py
ingestion/ingestion_server/__init__.py
ingestion/ingestion_server/asset_rest_api.py
ingestion/ingestion_server/ingestion_app.py
ingestion/ingestion_server/ingestion_file_upload_rest_api.py
ingestion/ingestion_server/ingestion_globals.py
ingestion/ingestion_server/ingestion_rest_api_v2.py
ingestion/ingestion_server/ingestion_server.py
ingestion/ingestion_server/templates/manage_files.html
ingestion/ingestion_server/templates/response.html
ingestion/ingestion_server/templates/share.html
ingestion/ingestion_server/templates/upload.html
magen_ingestion_service-1.3a20.data/scripts/ingestion_server.py
magen_ingestion_service-1.3a20.dist-info/DESCRIPTION.rst
magen_ingestion_service-1.3a20.dist-info/METADATA
magen_ingestion_service-1.3a20.dist-info/RECORD
magen_ingestion_service-1.3a20.dist-info/WHEEL
magen_ingestion_service-1.3a20.dist-info/metadata.json
magen_ingestion_service-1.3a20.dist-info/top_level.txt
