Metadata-Version: 2.0
Name: magen-ingestion-service
Version: 1.3a20
Summary: Ingestion MicroService Package
Home-page: https://magengit.github.io/
Author: Reinaldo Penno
Author-email: rapenno@gmail.com
License: Apache Software License
Platform: UNKNOWN
Classifier: Development Status :: 2 - Pre-Alpha
Classifier: Intended Audience :: Education
Classifier: Intended Audience :: Financial and Insurance Industry
Classifier: Intended Audience :: Healthcare Industry
Classifier: Intended Audience :: Legal Industry
Classifier: Topic :: Security
Classifier: License :: OSI Approved :: Apache Software License
Classifier: Programming Language :: Python :: 3.6
Requires-Dist: aniso8601 (>=2.0.0)
Requires-Dist: coverage (>=4.5.1)
Requires-Dist: flake8 (>=3.3.0)
Requires-Dist: Flask (>=0.12.2)
Requires-Dist: Flask-Cors (>=3.0.3)
Requires-Dist: Flask-Login (>=0.4.1)
Requires-Dist: lxml (>=4.1.0)
Requires-Dist: pycrypto (>=2.6.1)
Requires-Dist: pymongo (>=3.4.0)
Requires-Dist: pytest (>=3.4.0)
Requires-Dist: requests (>=2.13.0)
Requires-Dist: responses (>=0.5.1)
Requires-Dist: Sphinx (>=1.6.3)
Requires-Dist: wheel (>=0.30.0a0)
Requires-Dist: prometheus-client (>=0.1.0)
Requires-Dist: magen-logger (>=1.0a1)
Requires-Dist: magen-utils (>=1.2a2)
Requires-Dist: magen-mongo (>=1.0a1)
Requires-Dist: magen-rest-service (>=1.3a6)
Requires-Dist: magen-user (>=0.0a6)
